{
    "tail_brush_red": "tail_brush_red",
    "tail_brush_orange": "tail_brush_orange",
    "tail_brush_black": "tail_brush_black",
    "tail_brush_gray": "tail_brush_gray",
    "tail_brush_purple": "tail_brush_purple",
    "tail_brush_white": "tail_brush_white",
    "tail_brush_yellow": "tail_brush_yellow",
    "tail_brush_brown": "tail_brush_brown",
    "tail_brush_blue": "tail_brush_blue",
    "tail_devil_red": "tail_devil_red",
    "tail_devil_orange": "tail_devil_orange",
    "tail_devil_black": "tail_devil_black",
    "tail_devil_gray": "tail_devil_gray",
    "tail_devil_purple": "tail_devil_purple",
    "tail_devil_white": "tail_devil_white",
    "tail_devil_yellow": "tail_devil_yellow",
    "tail_devil_brown": "tail_devil_brown",
    "tail_devil_blue": "tail_devil_blue",
    "tail_snake_red": "tail_snake_red",
    "tail_snake_orange": "tail_snake_orange",
    "tail_snake_black": "tail_snake_black",
    "tail_snake_gray": "tail_snake_gray",
    "tail_snake_purple": "tail_snake_purple",
    "tail_snake_white": "tail_snake_white",
    "tail_snake_yellow": "tail_snake_yellow",
    "tail_snake_brown": "tail_snake_brown",
    "tail_snake_blue": "tail_snake_blue",
    "tail_fluffy_red": "tail_fluffy_red",
    "tail_fluffy_orange": "tail_fluffy_orange",
    "tail_fluffy_black": "tail_fluffy_black",
    "tail_fluffy_gray": "tail_fluffy_gray",
    "tail_fluffy_purple": "tail_fluffy_purple",
    "tail_fluffy_white": "tail_fluffy_white",
    "tail_fluffy_yellow": "tail_fluffy_yellow",
    "tail_fluffy_brown": "tail_fluffy_brown",
    "tail_fluffy_blue": "tail_fluffy_blue",
    "tail_horse_red": "tail_horse_red",
    "tail_horse_orange": "tail_horse_orange",
    "tail_horse_black": "tail_horse_black",
    "tail_horse_gray": "tail_horse_gray",
    "tail_horse_purple": "tail_horse_purple",
    "tail_horse_white": "tail_horse_white",
    "tail_horse_yellow": "tail_horse_yellow",
    "tail_horse_brown": "tail_horse_brown",
    "tail_horse_blue": "tail_horse_blue",
    "tail_kitsune_red": "tail_kitsune_red",
    "tail_kitsune_orange": "tail_kitsune_orange",
    "tail_kitsune_black": "tail_kitsune_black",
    "tail_kitsune_gray": "tail_kitsune_gray",
    "tail_kitsune_purple": "tail_kitsune_purple",
    "tail_kitsune_white": "tail_kitsune_white",
    "tail_kitsune_yellow": "tail_kitsune_yellow",
    "tail_kitsune_brown": "tail_kitsune_brown",
    "tail_kitsune_blue": "tail_kitsune_blue",
    "tail_lion_red": "tail_lion_red",
    "tail_lion_orange": "tail_lion_orange",
    "tail_lion_black": "tail_lion_black",
    "tail_lion_gray": "tail_lion_gray",
    "tail_lion_purple": "tail_lion_purple",
    "tail_lion_white": "tail_lion_white",
    "tail_lion_yellow": "tail_lion_yellow",
    "tail_lion_brown": "tail_lion_brown",
    "tail_lion_blue": "tail_lion_blue",
    "tail_scorpion_red": "tail_scorpion_red",
    "tail_scorpion_orange": "tail_scorpion_orange",
    "tail_scorpion_black": "tail_scorpion_black",
    "tail_scorpion_gray": "tail_scorpion_gray",
    "tail_scorpion_purple": "tail_scorpion_purple",
    "tail_scorpion_white": "tail_scorpion_white",
    "tail_scorpion_yellow": "tail_scorpion_yellow",
    "tail_scorpion_brown": "tail_scorpion_brown",
    "tail_scorpion_blue": "tail_scorpion_blue",
    "tail_silky_red": "tail_silky_red",
    "tail_silky_orange": "tail_silky_orange",
    "tail_silky_black": "tail_silky_black",
    "tail_silky_gray": "tail_silky_gray",
    "tail_silky_purple": "tail_silky_purple",
    "tail_silky_white": "tail_silky_white",
    "tail_silky_yellow": "tail_silky_yellow",
    "tail_silky_brown": "tail_silky_brown",
    "tail_silky_blue": "tail_silky_blue",
    "tail_unicorn_red": "tail_unicorn_red",
    "tail_unicorn_orange": "tail_unicorn_orange",
    "tail_unicorn_black": "tail_unicorn_black",
    "tail_unicorn_gray": "tail_unicorn_gray",
    "tail_unicorn_purple": "tail_unicorn_purple",
    "tail_unicorn_white": "tail_unicorn_white",
    "tail_unicorn_yellow": "tail_unicorn_yellow",
    "tail_unicorn_brown": "tail_unicorn_brown",
    "tail_unicorn_blue": "tail_unicorn_blue",
    "leftbackleg_deer_red": "leftbackleg_deer_red",
    "leftbackleg_deer_orange": "leftbackleg_deer_orange",
    "leftbackleg_deer_black": "leftbackleg_deer_black",
    "leftbackleg_deer_blue": "leftbackleg_deer_blue",
    "leftbackleg_deer_brown": "leftbackleg_deer_brown",
    "leftbackleg_deer_gray": "leftbackleg_deer_gray",
    "leftbackleg_deer_purple": "leftbackleg_deer_purple",
    "leftbackleg_deer_white": "leftbackleg_deer_white",
    "leftbackleg_deer_yellow": "leftbackleg_deer_yellow",
    "leftbackleg_wolf_red": "leftbackleg_wolf_red",
    "leftbackleg_wolf_orange": "leftbackleg_wolf_orange",
    "leftbackleg_wolf_black": "leftbackleg_wolf_black",
    "leftbackleg_wolf_blue": "leftbackleg_wolf_blue",
    "leftbackleg_wolf_brown": "leftbackleg_wolf_brown",
    "leftbackleg_wolf_gray": "leftbackleg_wolf_gray",
    "leftbackleg_wolf_purple": "leftbackleg_wolf_purple",
    "leftbackleg_wolf_white": "leftbackleg_wolf_white",
    "leftbackleg_wolf_yellow": "leftbackleg_wolf_yellow",
    "leftbackleg_eagle_red": "leftbackleg_eagle_red",
    "leftbackleg_eagle_orange": "leftbackleg_eagle_orange",
    "leftbackleg_eagle_black": "leftbackleg_eagle_black",
    "leftbackleg_eagle_blue": "leftbackleg_eagle_blue",
    "leftbackleg_eagle_brown": "leftbackleg_eagle_brown",
    "leftbackleg_eagle_gray": "leftbackleg_eagle_gray",
    "leftbackleg_eagle_purple": "leftbackleg_eagle_purple",
    "leftbackleg_eagle_white": "leftbackleg_eagle_white",
    "leftbackleg_eagle_yellow": "leftbackleg_eagle_yellow",
    "leftbackleg_lion_red": "leftbackleg_lion_red",
    "leftbackleg_lion_orange": "leftbackleg_lion_orange",
    "leftbackleg_lion_black": "leftbackleg_lion_black",
    "leftbackleg_lion_blue": "leftbackleg_lion_blue",
    "leftbackleg_lion_brown": "leftbackleg_lion_brown",
    "leftbackleg_lion_gray": "leftbackleg_lion_gray",
    "leftbackleg_lion_purple": "leftbackleg_lion_purple",
    "leftbackleg_lion_white": "leftbackleg_lion_white",
    "leftbackleg_lion_yellow": "leftbackleg_lion_yellow",
    "leftbackleg_horse_red": "leftbackleg_horse_red",
    "leftbackleg_horse_orange": "leftbackleg_horse_orange",
    "leftbackleg_horse_black": "leftbackleg_horse_black",
    "leftbackleg_horse_blue": "leftbackleg_horse_blue",
    "leftbackleg_horse_brown": "leftbackleg_horse_brown",
    "leftbackleg_horse_gray": "leftbackleg_horse_gray",
    "leftbackleg_horse_purple": "leftbackleg_horse_purple",
    "leftbackleg_horse_white": "leftbackleg_horse_white",
    "leftbackleg_horse_yellow": "leftbackleg_horse_yellow",
    "leftbackleg_deer_medium": "leftbackleg_deer_medium",
    "leftbackleg_eagle_medium": "leftbackleg_eagle_medium",
    "leftbackleg_horse_medium": "leftbackleg_horse_medium",
    "leftbackleg_lion_medium": "leftbackleg_lion_medium",
    "leftbackleg_wolf_medium": "leftbackleg_wolf_medium",
    "leftbackleg_deer_shaggy": "leftbackleg_deer_shaggy",
    "leftbackleg_eagle_shaggy": "leftbackleg_eagle_shaggy",
    "leftbackleg_horse_shaggy": "leftbackleg_horse_shaggy",
    "leftbackleg_lion_shaggy": "leftbackleg_lion_shaggy",
    "leftbackleg_wolf_shaggy": "leftbackleg_wolf_shaggy",
    "leftfrontleg_deer_red": "leftfrontleg_deer_red",
    "leftfrontleg_deer_orange": "leftfrontleg_deer_orange",
    "leftfrontleg_deer_black": "leftfrontleg_deer_black",
    "leftfrontleg_deer_blue": "leftfrontleg_deer_blue",
    "leftfrontleg_deer_brown": "leftfrontleg_deer_brown",
    "leftfrontleg_deer_gray": "leftfrontleg_deer_gray",
    "leftfrontleg_deer_purple": "leftfrontleg_deer_purple",
    "leftfrontleg_deer_white": "leftfrontleg_deer_white",
    "leftfrontleg_deer_yellow": "leftfrontleg_deer_yellow",
    "leftfrontleg_wolf_red": "leftfrontleg_wolf_red",
    "leftfrontleg_wolf_orange": "leftfrontleg_wolf_orange",
    "leftfrontleg_wolf_black": "leftfrontleg_wolf_black",
    "leftfrontleg_wolf_blue": "leftfrontleg_wolf_blue",
    "leftfrontleg_wolf_brown": "leftfrontleg_wolf_brown",
    "leftfrontleg_wolf_gray": "leftfrontleg_wolf_gray",
    "leftfrontleg_wolf_purple": "leftfrontleg_wolf_purple",
    "leftfrontleg_wolf_white": "leftfrontleg_wolf_white",
    "leftfrontleg_wolf_yellow": "leftfrontleg_wolf_yellow",
    "leftfrontleg_eagle_red": "leftfrontleg_eagle_red",
    "leftfrontleg_eagle_orange": "leftfrontleg_eagle_orange",
    "leftfrontleg_eagle_black": "leftfrontleg_eagle_black",
    "leftfrontleg_eagle_blue": "leftfrontleg_eagle_blue",
    "leftfrontleg_eagle_brown": "leftfrontleg_eagle_brown",
    "leftfrontleg_eagle_gray": "leftfrontleg_eagle_gray",
    "leftfrontleg_eagle_purple": "leftfrontleg_eagle_purple",
    "leftfrontleg_eagle_white": "leftfrontleg_eagle_white",
    "leftfrontleg_eagle_yellow": "leftfrontleg_eagle_yellow",
    "leftfrontleg_lion_red": "leftfrontleg_lion_red",
    "leftfrontleg_lion_orange": "leftfrontleg_lion_orange",
    "leftfrontleg_lion_black": "leftfrontleg_lion_black",
    "leftfrontleg_lion_blue": "leftfrontleg_lion_blue",
    "leftfrontleg_lion_brown": "leftfrontleg_lion_brown",
    "leftfrontleg_lion_gray": "leftfrontleg_lion_gray",
    "leftfrontleg_lion_purple": "leftfrontleg_lion_purple",
    "leftfrontleg_lion_white": "leftfrontleg_lion_white",
    "leftfrontleg_lion_yellow": "leftfrontleg_lion_yellow",
    "leftfrontleg_horse_red": "leftfrontleg_horse_red",
    "leftfrontleg_horse_orange": "leftfrontleg_horse_orange",
    "leftfrontleg_horse_black": "leftfrontleg_horse_black",
    "leftfrontleg_horse_blue": "leftfrontleg_horse_blue",
    "leftfrontleg_horse_brown": "leftfrontleg_horse_brown",
    "leftfrontleg_horse_gray": "leftfrontleg_horse_gray",
    "leftfrontleg_horse_purple": "leftfrontleg_horse_purple",
    "leftfrontleg_horse_white": "leftfrontleg_horse_white",
    "leftfrontleg_horse_yellow": "leftfrontleg_horse_yellow",
    "back_featherwings_red": "back_featherwings_red",
    "back_featherwings_orange": "back_featherwings_orange",
    "back_featherwings_yellow": "back_featherwings_yellow",
    "back_featherwings_blue": "back_featherwings_blue",
    "back_featherwings_purple": "back_featherwings_purple",
    "back_featherwings_brown": "back_featherwings_brown",
    "back_featherwings_gray": "back_featherwings_gray",
    "back_featherwings_black": "back_featherwings_black",
    "back_featherwings_white": "back_featherwings_white",
    "back_dragonwings_black": "back_dragonwings_black",
    "back_dragonwings_blue": "back_dragonwings_blue",
    "back_dragonwings_brown": "back_dragonwings_brown",
    "back_dragonwings_gray": "back_dragonwings_gray",
    "back_dragonwings_orange": "back_dragonwings_orange",
    "back_dragonwings_purple": "back_dragonwings_purple",
    "back_dragonwings_red": "back_dragonwings_red",
    "back_dragonwings_white": "back_dragonwings_white",
    "back_dragonwings_yellow": "back_dragonwings_yellow",
    "back_spike_red": "back_spike_red",
    "back_spike_black": "back_spike_black",
    "back_spike_blue": "back_spike_blue",
    "back_spike_white": "back_spike_white",
    "back_spike_yellow": "back_spike_yellow",
    "back_spike_purple": "back_spike_purple",
    "back_spike_brown": "back_spike_brown",
    "back_spike_gray": "back_spike_gray",
    "back_spike_orange": "back_spike_orange",
    "torsobase_medium_black": "torsobase_medium_black",
    "torsobase_medium_blue": "torsobase_medium_blue",
    "torsobase_medium_brown": "torsobase_medium_brown",
    "torsobase_medium_gray": "torsobase_medium_gray",
    "torsobase_medium_orange": "torsobase_medium_orange",
    "torsobase_medium_purple": "torsobase_medium_purple",
    "torsobase_medium_red": "torsobase_medium_red",
    "torsobase_medium_white": "torsobase_medium_white",
    "torsobase_medium_yellow": "torsobase_medium_yellow",
    "torsobase_shaggy_black": "torsobase_shaggy_black",
    "torsobase_shaggy_blue": "torsobase_shaggy_blue",
    "torsobase_shaggy_brown": "torsobase_shaggy_brown",
    "torsobase_shaggy_gray": "torsobase_shaggy_gray",
    "torsobase_shaggy_orange": "torsobase_shaggy_orange",
    "torsobase_shaggy_purple": "torsobase_shaggy_purple",
    "torsobase_shaggy_red": "torsobase_shaggy_red",
    "torsobase_shaggy_white": "torsobase_shaggy_white",
    "torsobase_shaggy_yellow": "torsobase_shaggy_yellow",
    "torsoaccent_medium_white": "torsoaccent_medium_white",
    "torsoaccent_shaggy_white": "torsoaccent_shaggy_white",
    "torsopattern_spripes_black": "torsopattern_spripes_black",
    "torsopattern_spots_black": "torsopattern_spots_black",
    "neckbase_regular_red": "neckbase_regular_red",
    "neckbase_regular_orange": "neckbase_regular_orange",
    "neckbase_regular_black": "neckbase_regular_black",
    "neckbase_regular_blue": "neckbase_regular_blue",
    "neckbase_regular_brown": "neckbase_regular_brown",
    "neckbase_regular_gray": "neckbase_regular_gray",
    "neckbase_regular_white": "neckbase_regular_white",
    "neckbase_regular_purple": "neckbase_regular_purple",
    "neckbase_regular_yellow": "neckbase_regular_yellow",
    "neckaccent_throat_white": "neckaccent_throat_white",
    "neckpattern_stripes_white": "neckpattern_stripes_white",
    "neckpattern_spots_white": "neckpattern_spots_white",
    "neckshadow_bear_black": "neckshadow_bear_black",
    "neckshadow_horse_black": "neckshadow_horse_black",
    "neckshadow_lion_black": "neckshadow_lion_black",
    "neckshadow_wolf_black": "neckshadow_wolf_black",
    "fur_bushy_black": "fur_bushy_black",
    "fur_bushy_blue": "fur_bushy_blue",
    "fur_bushy_brown": "fur_bushy_brown",
    "fur_bushy_gray": "fur_bushy_gray",
    "fur_bushy_orange": "fur_bushy_orange",
    "fur_bushy_purple": "fur_bushy_purple",
    "fur_bushy_red": "fur_bushy_red",
    "fur_bushy_white": "fur_bushy_white",
    "fur_bushy_yellow": "fur_bushy_yellow",
    "fur_wooly_black": "fur_wooly_black",
    "fur_wooly_blue": "fur_wooly_blue",
    "fur_wooly_brown": "fur_wooly_brown",
    "fur_wooly_gray": "fur_wooly_gray",
    "fur_wooly_orange": "fur_wooly_orange",
    "fur_wooly_purple": "fur_wooly_purple",
    "fur_wooly_red": "fur_wooly_red",
    "fur_wooly_white": "fur_wooly_white",
    "fur_wooly_yellow": "fur_wooly_yellow",
    "fur_silky_black": "fur_silky_black",
    "fur_silky_blue": "fur_silky_blue",
    "fur_silky_brown": "fur_silky_brown",
    "fur_silky_gray": "fur_silky_gray",
    "fur_silky_orange": "fur_silky_orange",
    "fur_silky_purple": "fur_silky_purple",
    "fur_silky_red": "fur_silky_red",
    "fur_silky_white": "fur_silky_white",
    "fur_silky_yellow": "fur_silky_yellow",
    "fur_windy_black": "fur_windy_black",
    "fur_windy_blue": "fur_windy_blue",
    "fur_windy_brown": "fur_windy_brown",
    "fur_windy_gray": "fur_windy_gray",
    "fur_windy_orange": "fur_windy_orange",
    "fur_windy_purple": "fur_windy_purple",
    "fur_windy_red": "fur_windy_red",
    "fur_windy_white": "fur_windy_white",
    "fur_windy_yellow": "fur_windy_yellow",
    "rightbackleg_eagle_red": "rightbackleg_eagle_red",
    "rightbackleg_eagle_orange": "rightbackleg_eagle_orange",
    "rightbackleg_eagle_black": "rightbackleg_eagle_black",
    "rightbackleg_eagle_blue": "rightbackleg_eagle_blue",
    "rightbackleg_eagle_brown": "rightbackleg_eagle_brown",
    "rightbackleg_eagle_gray": "rightbackleg_eagle_gray",
    "rightbackleg_eagle_purple": "rightbackleg_eagle_purple",
    "rightbackleg_eagle_white": "rightbackleg_eagle_white",
    "rightbackleg_eagle_yellow": "rightbackleg_eagle_yellow",
    "rightbackleg_wolf_red": "rightbackleg_wolf_red",
    "rightbackleg_wolf_orange": "rightbackleg_wolf_orange",
    "rightbackleg_wolf_black": "rightbackleg_wolf_black",
    "rightbackleg_wolf_blue": "rightbackleg_wolf_blue",
    "rightbackleg_wolf_brown": "rightbackleg_wolf_brown",
    "rightbackleg_wolf_gray": "rightbackleg_wolf_gray",
    "rightbackleg_wolf_purple": "rightbackleg_wolf_purple",
    "rightbackleg_wolf_white": "rightbackleg_wolf_white",
    "rightbackleg_wolf_yellow": "rightbackleg_wolf_yellow",
    "rightbackleg_deer_red": "rightbackleg_deer_red",
    "rightbackleg_deer_orange": "rightbackleg_deer_orange",
    "rightbackleg_deer_black": "rightbackleg_deer_black",
    "rightbackleg_deer_blue": "rightbackleg_deer_blue",
    "rightbackleg_deer_brown": "rightbackleg_deer_brown",
    "rightbackleg_deer_gray": "rightbackleg_deer_gray",
    "rightbackleg_deer_purple": "rightbackleg_deer_purple",
    "rightbackleg_deer_white": "rightbackleg_deer_white",
    "rightbackleg_deer_yellow": "rightbackleg_deer_yellow",
    "rightbackleg_horse_red": "rightbackleg_horse_red",
    "rightbackleg_horse_orange": "rightbackleg_horse_orange",
    "rightbackleg_horse_black": "rightbackleg_horse_black",
    "rightbackleg_horse_blue": "rightbackleg_horse_blue",
    "rightbackleg_horse_brown": "rightbackleg_horse_brown",
    "rightbackleg_horse_gray": "rightbackleg_horse_gray",
    "rightbackleg_horse_purple": "rightbackleg_horse_purple",
    "rightbackleg_horse_white": "rightbackleg_horse_white",
    "rightbackleg_horse_yellow": "rightbackleg_horse_yellow",
    "rightbackleg_lion_red": "rightbackleg_lion_red",
    "rightbackleg_lion_orange": "rightbackleg_lion_orange",
    "rightbackleg_lion_black": "rightbackleg_lion_black",
    "rightbackleg_lion_blue": "rightbackleg_lion_blue",
    "rightbackleg_lion_brown": "rightbackleg_lion_brown",
    "rightbackleg_lion_gray": "rightbackleg_lion_gray",
    "rightbackleg_lion_purple": "rightbackleg_lion_purple",
    "rightbackleg_lion_white": "rightbackleg_lion_white",
    "rightbackleg_lion_yellow": "rightbackleg_lion_yellow",
    "rightfrontleg_eagle_black": "rightfrontleg_eagle_black",
    "rightfrontleg_eagle_blue": "rightfrontleg_eagle_blue",
    "rightfrontleg_eagle_brown": "rightfrontleg_eagle_brown",
    "rightfrontleg_eagle_gray": "rightfrontleg_eagle_gray",
    "rightfrontleg_eagle_purple": "rightfrontleg_eagle_purple",
    "rightfrontleg_eagle_orange": "rightfrontleg_eagle_orange",
    "rightfrontleg_eagle_red": "rightfrontleg_eagle_red",
    "rightfrontleg_eagle_white": "rightfrontleg_eagle_white",
    "rightfrontleg_eagle_yellow": "rightfrontleg_eagle_yellow",
    "rightfrontleg_wolf_black": "rightfrontleg_wolf_black",
    "rightfrontleg_wolf_blue": "rightfrontleg_wolf_blue",
    "rightfrontleg_wolf_brown": "rightfrontleg_wolf_brown",
    "rightfrontleg_wolf_gray": "rightfrontleg_wolf_gray",
    "rightfrontleg_wolf_purple": "rightfrontleg_wolf_purple",
    "rightfrontleg_wolf_orange": "rightfrontleg_wolf_orange",
    "rightfrontleg_wolf_red": "rightfrontleg_wolf_red",
    "rightfrontleg_wolf_white": "rightfrontleg_wolf_white",
    "rightfrontleg_wolf_yellow": "rightfrontleg_wolf_yellow",
    "rightfrontleg_horse_black": "rightfrontleg_horse_black",
    "rightfrontleg_horse_blue": "rightfrontleg_horse_blue",
    "rightfrontleg_horse_brown": "rightfrontleg_horse_brown",
    "rightfrontleg_horse_gray": "rightfrontleg_horse_gray",
    "rightfrontleg_horse_purple": "rightfrontleg_horse_purple",
    "rightfrontleg_horse_orange": "rightfrontleg_horse_orange",
    "rightfrontleg_horse_red": "rightfrontleg_horse_red",
    "rightfrontleg_horse_white": "rightfrontleg_horse_white",
    "rightfrontleg_horse_yellow": "rightfrontleg_horse_yellow",
    "rightfrontleg_deer_black": "rightfrontleg_deer_black",
    "rightfrontleg_deer_blue": "rightfrontleg_deer_blue",
    "rightfrontleg_deer_brown": "rightfrontleg_deer_brown",
    "rightfrontleg_deer_gray": "rightfrontleg_deer_gray",
    "rightfrontleg_deer_purple": "rightfrontleg_deer_purple",
    "rightfrontleg_deer_orange": "rightfrontleg_deer_orange",
    "rightfrontleg_deer_red": "rightfrontleg_deer_red",
    "rightfrontleg_deer_white": "rightfrontleg_deer_white",
    "rightfrontleg_deer_yellow": "rightfrontleg_deer_yellow",
    "rightfrontleg_lion_black": "rightfrontleg_lion_black",
    "rightfrontleg_lion_blue": "rightfrontleg_lion_blue",
    "rightfrontleg_lion_brown": "rightfrontleg_lion_brown",
    "rightfrontleg_lion_gray": "rightfrontleg_lion_gray",
    "rightfrontleg_lion_purple": "rightfrontleg_lion_purple",
    "rightfrontleg_lion_orange": "rightfrontleg_lion_orange",
    "rightfrontleg_lion_red": "rightfrontleg_lion_red",
    "rightfrontleg_lion_white": "rightfrontleg_lion_white",
    "rightfrontleg_lion_yellow": "rightfrontleg_lion_yellow",
    "ears_lamb_red": "ears_lamb_red",
    "ears_lamb_orange": "ears_lamb_orange",
    "ears_lamb_purple": "ears_lamb_purple",
    "ears_lamb_yellow": "ears_lamb_yellow",
    "ears_lamb_white": "ears_lamb_white",
    "ears_lamb_blue": "ears_lamb_blue",
    "ears_lamb_black": "ears_lamb_black",
    "ears_lamb_brown": "ears_lamb_brown",
    "ears_lamb_gray": "ears_lamb_gray",
    "ears_prick_red": "ears_prick_red",
    "ears_prick_orange": "ears_prick_orange",
    "ears_prick_purple": "ears_prick_purple",
    "ears_prick_black": "ears_prick_black",
    "ears_prick_brown": "ears_prick_brown",
    "ears_prick_yellow": "ears_prick_yellow",
    "ears_prick_blue": "ears_prick_blue",
    "ears_prick_white": "ears_prick_white",
    "ears_prick_gray": "ears_prick_gray",
    "ears_feather_red": "ears_feather_red",
    "ears_feather_orange": "ears_feather_orange",
    "ears_feather_purple": "ears_feather_purple",
    "ears_feather_yellow": "ears_feather_yellow",
    "ears_feather_white": "ears_feather_white",
    "ears_feather_blue": "ears_feather_blue",
    "ears_feather_black": "ears_feather_black",
    "ears_feather_brown": "ears_feather_brown",
    "ears_feather_gray": "ears_feather_gray",
    "ears_flop_red": "ears_flop_red",
    "ears_flop_orange": "ears_flop_orange",
    "ears_flop_purple": "ears_flop_purple",
    "ears_flop_yellow": "ears_flop_yellow",
    "ears_flop_white": "ears_flop_white",
    "ears_flop_blue": "ears_flop_blue",
    "ears_flop_black": "ears_flop_black",
    "ears_flop_brown": "ears_flop_brown",
    "ears_flop_gray": "ears_flop_gray",
    "ears_lynx_red": "ears_lynx_red",
    "ears_lynx_orange": "ears_lynx_orange",
    "ears_lynx_purple": "ears_lynx_purple",
    "ears_lynx_yellow": "ears_lynx_yellow",
    "ears_lynx_white": "ears_lynx_white",
    "ears_lynx_blue": "ears_lynx_blue",
    "ears_lynx_black": "ears_lynx_black",
    "ears_lynx_brown": "ears_lynx_brown",
    "ears_lynx_gray": "ears_lynx_gray",
    "ears_round_red": "ears_round_red",
    "ears_round_orange": "ears_round_orange",
    "ears_round_purple": "ears_round_purple",
    "ears_round_yellow": "ears_round_yellow",
    "ears_round_white": "ears_round_white",
    "ears_round_blue": "ears_round_blue",
    "ears_round_black": "ears_round_black",
    "ears_round_brown": "ears_round_brown",
    "ears_round_gray": "ears_round_gray",
    "ears_fox_red": "ears_fox_red",
    "ears_fox_orange": "ears_fox_orange",
    "ears_fox_purple": "ears_fox_purple",
    "ears_fox_yellow": "ears_fox_yellow",
    "ears_fox_white": "ears_fox_white",
    "ears_fox_blue": "ears_fox_blue",
    "ears_fox_black": "ears_fox_black",
    "ears_fox_brown": "ears_fox_brown",
    "ears_fox_gray": "ears_fox_gray",
    "headbase_bear_black": "headbase_bear_black",
    "headbase_bear_blue": "headbase_bear_blue",
    "headbase_bear_brown": "headbase_bear_brown",
    "headbase_bear_gray": "headbase_bear_gray",
    "headbase_bear_orange": "headbase_bear_orange",
    "headbase_bear_purple": "headbase_bear_purple",
    "headbase_bear_red": "headbase_bear_red",
    "headbase_bear_white": "headbase_bear_white",
    "headbase_bear_yellow": "headbase_bear_yellow",
    "headbase_eagle_black": "headbase_eagle_black",
    "headbase_eagle_blue": "headbase_eagle_blue",
    "headbase_eagle_brown": "headbase_eagle_brown",
    "headbase_eagle_gray": "headbase_eagle_gray",
    "headbase_eagle_orange": "headbase_eagle_orange",
    "headbase_eagle_purple": "headbase_eagle_purple",
    "headbase_eagle_red": "headbase_eagle_red",
    "headbase_eagle_white": "headbase_eagle_white",
    "headbase_eagle_yellow": "headbase_eagle_yellow",
    "headbase_horse_black": "headbase_horse_black",
    "headbase_horse_blue": "headbase_horse_blue",
    "headbase_horse_brown": "headbase_horse_brown",
    "headbase_horse_gray": "headbase_horse_gray",
    "headbase_horse_orange": "headbase_horse_orange",
    "headbase_horse_purple": "headbase_horse_purple",
    "headbase_horse_red": "headbase_horse_red",
    "headbase_horse_white": "headbase_horse_white",
    "headbase_horse_yellow": "headbase_horse_yellow",
    "headbase_lion_black": "headbase_lion_black",
    "headbase_lion_blue": "headbase_lion_blue",
    "headbase_lion_brown": "headbase_lion_brown",
    "headbase_lion_gray": "headbase_lion_gray",
    "headbase_lion_orange": "headbase_lion_orange",
    "headbase_lion_purple": "headbase_lion_purple",
    "headbase_lion_red": "headbase_lion_red",
    "headbase_lion_white": "headbase_lion_white",
    "headbase_lion_yellow": "headbase_lion_yellow",
    "headbase_wolf_black": "headbase_wolf_black",
    "headbase_wolf_blue": "headbase_wolf_blue",
    "headbase_wolf_brown": "headbase_wolf_brown",
    "headbase_wolf_gray": "headbase_wolf_gray",
    "headbase_wolf_orange": "headbase_wolf_orange",
    "headbase_wolf_purple": "headbase_wolf_purple",
    "headbase_wolf_red": "headbase_wolf_red",
    "headbase_wolf_white": "headbase_wolf_white",
    "headbase_wolf_yellow": "headbase_wolf_yellow",
    "headaccent_bear_blaze_white": "headaccent_bear_blaze_white",
    "headaccent_bear_face_white": "headaccent_bear_face_white",
    "headaccent_bear_mask_white": "headaccent_bear_mask_white",
    "headaccent_bear_points_white": "headaccent_bear_points_white",
    "headaccent_bear_star_white": "headaccent_bear_star_white",
    "headaccent_eagle_blaze_white": "headaccent_eagle_blaze_white",
    "headaccent_eagle_face_white": "headaccent_eagle_face_white",
    "headaccent_eagle_mask_white": "headaccent_eagle_mask_white",
    "headaccent_eagle_points_white": "headaccent_eagle_points_white",
    "headaccent_eagle_star_white": "headaccent_eagle_star_white",
    "headaccent_horse_blaze_white": "headaccent_horse_blaze_white",
    "headaccent_horse_face_white": "headaccent_horse_face_white",
    "headaccent_horse_mask_white": "headaccent_horse_mask_white",
    "headaccent_horse_points_white": "headaccent_horse_points_white",
    "headaccent_horse_star_white": "headaccent_horse_star_white",
    "headaccent_lion_blaze_white": "headaccent_lion_blaze_white",
    "headaccent_lion_face_white": "headaccent_lion_face_white",
    "headaccent_lion_mask_white": "headaccent_lion_mask_white",
    "headaccent_lion_points_white": "headaccent_lion_points_white",
    "headaccent_lion_star_white": "headaccent_lion_star_white",
    "headaccent_wolf_blaze_white": "headaccent_wolf_blaze_white",
    "headaccent_wolf_face_white": "headaccent_wolf_face_white",
    "headaccent_wolf_mask_white": "headaccent_wolf_mask_white",
    "headaccent_wolf_points_white": "headaccent_wolf_points_white",
    "headaccent_wolf_star_white": "headaccent_wolf_star_white",
    "headpattern_bear_stripes": "headpattern_bear_stripes",
    "headpattern_bear_spots": "headpattern_bear_spots",
    "headpattern_eagle_stripes": "headpattern_eagle_stripes",
    "headpattern_eagle_spots": "headpattern_eagle_spots",
    "headpattern_horse_stripes": "headpattern_horse_stripes",
    "headpattern_horse_spots": "headpattern_horse_spots",
    "headpattern_lion_stripes": "headpattern_lion_stripes",
    "headpattern_lion_spots": "headpattern_lion_spots",
    "headpattern_wolf_stripes": "headpattern_wolf_stripes",
    "headpattern_wolf_spots": "headpattern_wolf_spots",
    "mouth_bear_empty": "mouth_bear_empty",
    "mouth_eagle_empty": "mouth_eagle_empty",
    "mouth_horse_teeth": "mouth_horse_teeth",
    "mouth_horse_empty": "mouth_horse_empty",
    "mouth_lion_empty": "mouth_lion_empty",
    "mouth_lion_teeth": "mouth_lion_teeth",
    "mouth_wolf_empty": "mouth_wolf_empty",
    "horns_ram_light": "horns_ram_light",
    "horns_ram_medium": "horns_ram_medium",
    "horns_ram_dark": "horns_ram_dark",
    "horns_unicorn_light": "horns_unicorn_light",
    "horns_unicorn_medium": "horns_unicorn_medium",
    "horns_unicorn_dark": "horns_unicorn_dark",
    "horns_goat_light": "horns_goat_light",
    "horns_goat_medium": "horns_goat_medium",
    "horns_goat_dark": "horns_goat_dark",
    "horns_bull_light": "horns_bull_light",
    "horns_bull_medium": "horns_bull_medium",
    "horns_bull_dark": "horns_bull_dark",
    "horns_antlers_light": "horns_antlers_light",
    "horns_antlers_medium": "horns_antlers_medium",
    "horns_antlers_dark": "horns_antlers_dark",
    "eyes_beast_blue": "eyes_beast_blue",
    "eyes_beast_brown": "eyes_beast_brown",
    "eyes_beast_gray": "eyes_beast_gray",
    "eyes_beast_green": "eyes_beast_green",
    "eyes_beast_orange": "eyes_beast_orange",
    "eyes_beast_pink": "eyes_beast_pink",
    "eyes_beast_purple": "eyes_beast_purple",
    "eyes_beast_red": "eyes_beast_red",
    "eyes_beast_yellow": "eyes_beast_yellow",
    "eyes_beast_white": "eyes_beast_white",
    "eyes_predator_blue": "eyes_predator_blue",
    "eyes_predator_brown": "eyes_predator_brown",
    "eyes_predator_gray": "eyes_predator_gray",
    "eyes_predator_green": "eyes_predator_green",
    "eyes_predator_orange": "eyes_predator_orange",
    "eyes_predator_pink": "eyes_predator_pink",
    "eyes_predator_purple": "eyes_predator_purple",
    "eyes_predator_red": "eyes_predator_red",
    "eyes_predator_yellow": "eyes_predator_yellow",
    "eyes_predator_white": "eyes_predator_white",
    "eyes_prey_blue": "eyes_prey_blue",
    "eyes_prey_brown": "eyes_prey_brown",
    "eyes_prey_gray": "eyes_prey_gray",
    "eyes_prey_green": "eyes_prey_green",
    "eyes_prey_orange": "eyes_prey_orange",
    "eyes_prey_pink": "eyes_prey_pink",
    "eyes_prey_purple": "eyes_prey_purple",
    "eyes_prey_red": "eyes_prey_red",
    "eyes_prey_yellow": "eyes_prey_yellow",
    "eyes_prey_white": "eyes_prey_white",
    "eyes_wise_blue": "eyes_wise_blue",
    "eyes_wise_brown": "eyes_wise_brown",
    "eyes_wise_gray": "eyes_wise_gray",
    "eyes_wise_green": "eyes_wise_green",
    "eyes_wise_orange": "eyes_wise_orange",
    "eyes_wise_pink": "eyes_wise_pink",
    "eyes_wise_purple": "eyes_wise_purple",
    "eyes_wise_red": "eyes_wise_red",
    "eyes_wise_yellow": "eyes_wise_yellow",
    "eyes_wise_white": "eyes_wise_white",
    "red": "red",
    "orange": "orange",
    "yellow": "yellow",
    "blue": "blue",
    "purple": "purple",
    "brown": "brown",
    "gray": "gray",
    "black": "black",
    "white": "white",
    "apricot": "apricot",
    "navy": "navy",
    "purp2": "purp2",
    "sky": "sky",
    "skyish": "skyish",
    "varsity": "varsity",
    "sand2": "sand2",
    "tan_egg_dark": "tan_egg_dark",
    "tan_egg_light": "tan_egg_light",
    "rose": "rose",
    "turq": "turq",
    "1_tail": "1_tail",
    "2_leftbackleg": "2_leftbackleg",
    "2a_leftbackleg_shadow_medium": "2a_leftbackleg_shadow_medium",
    "2b_leftbackleg_shadow_shaggy": "2b_leftbackleg_shadow_shaggy",
    "3_leftfrontleg": "3_leftfrontleg",
    "4_back": "4_back",
    "5a_torsobase": "5a_torsobase",
    "5b_torsoaccent": "5b_torsoaccent",
    "5c_torsopattern": "5c_torsopattern",
    "6a_neckbase": "6a_neckbase",
    "6b_neckaccent": "6b_neckaccent",
    "6c_neckpattern": "6c_neckpattern",
    "6d_neckshadow": "6d_neckshadow",
    "7_fur": "7_fur",
    "8_rightbackleg": "8_rightbackleg",
    "9_rightfrontleg": "9_rightfrontleg",
    "10_ears": "10_ears",
    "11a_headbase": "11a_headbase",
    "11b_headaccent": "11b_headaccent",
    "11c_headpattern": "11c_headpattern",
    "12_mouth": "12_mouth",
    "13_horns": "13_horns",
    "14_eyes": "14_eyes",
    "base_color": "base_color",
    "background": "Background"
}